functions/f1.v
module f1(a, b, c, f);
input a, b, c;
output f;

assign f = (~a & b) | (b & ~c) | (~b & ~c);

endmodule

functions/f1_tb.v
module f1_tb;
reg a, b, c;
wire f;

f1 func(.a(a), .b(b), .c(c), .f(f));

initial begin
    $monitor("a = %b, b = %b, c = %b, f = %b", a, b, c, f);
    $dumpfile("f1_tb.vcd");
    $dumpvars(0, f1_tb);

    a = 0;
    b = 0;
    c = 0;
    #1
    a = 0;
    b = 0;
    c = 1;
    #1
    a = 0;
    b = 1;
    c = 0;
    #1
    a = 0;
    b = 1;
    c = 1;
    #1
    a = 1;
    b = 0;
    c = 0;
    #1
    a = 1;
    b = 0;
    c = 1;
    #1
    a = 1;
    b = 1;
    c = 0;
    #1
    a = 1;
    b = 1;
    c = 1;
    #1;
end

endmodule

functions/f1_tb.vcd
$date
	Fri Jul 29 16:40:47 2022
$end
$version
	Icarus Verilog
$end
$timescale
	1s
$end
$scope module f1_tb $end
$var wire 1 ! f $end
$var reg 1 " a $end
$var reg 1 # b $end
$var reg 1 $ c $end
$scope module func $end
$var wire 1 " a $end
$var wire 1 # b $end
$var wire 1 $ c $end
$var wire 1 ! f $end
$upscope $end
$upscope $end
$enddefinitions $end
#0
$dumpvars
0$
0#
0"
1!
$end
#1
0!
1$
#2
1!
0$
1#
#3
1$
#4
0$
0#
1"
#5
0!
1$
#6
1!
0$
1#
#7
0!
1$
