functions/f2.v
module f2(a, b, c, d, f);

input a, b, c, d;
output reg f;

always@(a, b, c, d)
begin
    f = 0;
    case ({a, b, c, d})
    4'b0000, 4'b0001, 4'b0010, 4'b0100, 4'b0101, 4'b0111, 4'b1011, 4'b1111: f = 1;
    endcase

end

endmodule

functions/f2_tb.v
module f2_tb;
reg a, b, c, d;
wire f;

f2 func(.a(a), .b(b), .c(c), .d(d), .f(f));

initial begin
    $monitor("a = %b, b = %b, c = %b, d = %b, f = %b", a, b, c, d, f);
    $dumpfile("f2_tb.vcd");
    $dumpvars(0, f2_tb);

    a = 0;
    b = 0;
    c = 0;
    d = 0;
    #1
    a = 0;
    b = 0;
    c = 0;
    d = 1;
    #1
    a = 0;
    b = 0;
    c = 1;
    d = 0;
    #1
    a = 0;
    b = 0;
    c = 1;
    d = 1;
    #1
    a = 0;
    b = 1;
    c = 0;
    d = 0;
    #1
    a = 0;
    b = 1;
    c = 0;
    d = 1;
    #1
    a = 0;
    b = 1;
    c = 1;
    d = 0;
    #1
    a = 0;
    b = 1;
    c = 1;
    d = 1;
    #1
    a = 1;
    b = 0;
    c = 0;
    d = 0;
    #1
    a = 1;
    b = 0;
    c = 0;
    d = 1;
    #1
    a = 1;
    b = 0;
    c = 1;
    d = 0;
    #1
    a = 1;
    b = 0;
    c = 1;
    d = 1;
    #1
    a = 1;
    b = 1;
    c = 0;
    d = 0;
    #1
    a = 1;
    b = 1;
    c = 0;
    d = 1;
    #1
    a = 1;
    b = 1;
    c = 1;
    d = 0;
    #1
    a = 1;
    b = 1;
    c = 1;
    d = 1;
    #1;
end

endmodule

functions/f2_tb.vcd
$date
	Fri Jul 29 23:11:19 2022
$end
$version
	Icarus Verilog
$end
$timescale
	1s
$end
$scope module f2_tb $end
$var wire 1 ! f $end
$var reg 1 " a $end
$var reg 1 # b $end
$var reg 1 $ c $end
$var reg 1 % d $end
$scope module func $end
$var wire 1 " a $end
$var wire 1 # b $end
$var wire 1 $ c $end
$var wire 1 % d $end
$var reg 1 ! f $end
$upscope $end
$upscope $end
$enddefinitions $end
#0
$dumpvars
0%
0$
0#
0"
1!
$end
#1
1!
1%
#2
1!
0%
1$
#3
0!
1%
#4
1!
0%
0$
1#
#5
1!
1%
#6
0!
0%
1$
#7
1!
1%
#8
0!
0%
0$
0#
1"
#9
1%
#10
0%
1$
#11
1!
1%
#12
0!
0%
0$
1#
#13
1%
#14
0%
1$
#15
1!
1%
