functions/f3.v
module f3(a, b, c, d, f);

input a, b, c, d;
output f;

assign f = (a & ~c)  | (~b & d) | (~a & c & d) | (a & b & c & d);

endmodule

functions/f3_tb.v
module f3_tb;
reg a, b, c, d;
wire f;

f3 func(.a(a), .b(b), .c(c), .d(d), .f(f));

initial begin
    $monitor("a = %b, b = %b, c = %b, d = %b, f = %b", a, b, c, d, f);
    $dumpfile("f3_tb.vcd");
    $dumpvars(0, f3_tb);

    a = 0;
    b = 0;
    c = 0;
    d = 0;
    #1
    a = 0;
    b = 0;
    c = 0;
    d = 1;
    #1
    a = 0;
    b = 0;
    c = 1;
    d = 0;
    #1
    a = 0;
    b = 0;
    c = 1;
    d = 1;
    #1
    a = 0;
    b = 1;
    c = 0;
    d = 0;
    #1
    a = 0;
    b = 1;
    c = 0;
    d = 1;
    #1
    a = 0;
    b = 1;
    c = 1;
    d = 0;
    #1
    a = 0;
    b = 1;
    c = 1;
    d = 1;
    #1
    a = 1;
    b = 0;
    c = 0;
    d = 0;
    #1
    a = 1;
    b = 0;
    c = 0;
    d = 1;
    #1
    a = 1;
    b = 0;
    c = 1;
    d = 0;
    #1
    a = 1;
    b = 0;
    c = 1;
    d = 1;
    #1
    a = 1;
    b = 1;
    c = 0;
    d = 0;
    #1
    a = 1;
    b = 1;
    c = 0;
    d = 1;
    #1
    a = 1;
    b = 1;
    c = 1;
    d = 0;
    #1
    a = 1;
    b = 1;
    c = 1;
    d = 1;
    #1;
end

endmodule

functions/f3_tb.vcd
$date
	Fri Jul 29 23:28:20 2022
$end
$version
	Icarus Verilog
$end
$timescale
	1s
$end
$scope module f3_tb $end
$var wire 1 ! f $end
$var reg 1 " a $end
$var reg 1 # b $end
$var reg 1 $ c $end
$var reg 1 % d $end
$scope module func $end
$var wire 1 " a $end
$var wire 1 # b $end
$var wire 1 $ c $end
$var wire 1 % d $end
$var wire 1 ! f $end
$upscope $end
$upscope $end
$enddefinitions $end
#0
$dumpvars
0%
0$
0#
0"
0!
$end
#1
1!
1%
#2
0!
0%
1$
#3
1!
1%
#4
0!
0%
0$
1#
#5
1%
#6
0%
1$
#7
1!
1%
#8
1!
0%
0$
0#
1"
#9
1%
#10
0!
0%
1$
#11
1!
1%
#12
0%
0$
1#
#13
1%
#14
0!
0%
1$
#15
1!
1%
