exp2/halfadder.v
module halfadder(input A,input B,output S,output C);

assign S = A^B;
assign C = A&B;

endmodule

dump/exp2/fulladderuhalf.v
`include "halfadder.v"

module fulladderuhalf(input A,input B,input Cin,output S,output Cout);

wire outS,outC,out2;
halfadder ha1(A,B,outS,outC);
halfadder ha2(outS,Cin,S,out2);
assign Cout = out2|outC;

endmodule

dump/exp2/fulladderuhalf_tb.v
module fulladderuhalf_tb;

wire S,Cout;
reg A,B,Cin;

fulladderuhalf c(.A(A),.B(B),.Cin(Cin),.S(S),.Cout(Cout));

initial
begin

$display("Full Adder");

$dumpfile("fulladderuhalf.vcd");
$dumpvars(0,fulladderuhalf_tb);
$monitor("A = %b | B = %b | Cin = %b | S = %b | Cout = %b",A,B,Cin,S,Cout);

A = 1'b0;
B = 1'b0;
Cin = 1'b0;
#2

Cin = 1'b1;
#2
Cin = 1'b0;
B = 1'b1;
#2
Cin = 1'b1;
#2
Cin = 1'b0;
B = 1'b0;
A = 1'b1;
#2

Cin = 1'b1;
#2
Cin = 1'b0;
B = 1'b1;
#2
Cin = 1'b1;

#2 $finish;
end

endmodule

dump/exp2/fulladderuhalf.vcd
$date
	Sat Jul 30 14:13:17 2022
$end
$version
	Icarus Verilog
$end
$timescale
	1s
$end
$scope module fulladderuhalf_tb $end
$var wire 1 ! S $end
$var wire 1 " Cout $end
$var reg 1 # A $end
$var reg 1 $ B $end
$var reg 1 % Cin $end
$scope module c $end
$var wire 1 # A $end
$var wire 1 $ B $end
$var wire 1 % Cin $end
$var wire 1 " Cout $end
$var wire 1 & outS $end
$var wire 1 ' outC $end
$var wire 1 ( out2 $end
$var wire 1 ! S $end
$scope module ha1 $end
$var wire 1 # A $end
$var wire 1 $ B $end
$var wire 1 ' C $end
$var wire 1 & S $end
$upscope $end
$scope module ha2 $end
$var wire 1 & A $end
$var wire 1 % B $end
$var wire 1 ( C $end
$var wire 1 ! S $end
$upscope $end
$upscope $end
$upscope $end
$enddefinitions $end
#0
$dumpvars
0(
0'
0&
0%
0$
0#
0"
0!
$end
#2
1!
1%
#4
1&
1!
1$
0%
#6
1"
0!
1(
1%
#8
0"
1!
0(
1#
0$
0%
#10
1"
0!
1(
1%
#12
0&
1'
0!
0(
1$
0%
#14
1!
1%
