adder/half_adder.v
module half_adder(a,b,sum,carry);
input a,b;
output sum, carry;

// gate level

xor xor_1(sum,a,b);
and and_1(carry,a,b);

endmodule

adder/full_adder.v
module full_adder(a,b,c,sum,carry);
input a,b,c;
output sum,carry;
wire s1, c1, c2;

half_adder ha1(.a(a), .b(b), .sum(s1), .carry(c1));
half_adder ha2(.a(s1), .b(c), .sum(sum), .carry(c2));
or or1(carry, c1, c2);

endmodule

adder/full_adder_tb.v
module full_adder_tb;
reg a,b,c;
wire sum,carry;

full_adder add1(a,b,c,sum,carry);

initial
begin
    $monitor("a = %b, b = %b, c = %b, sum = %b, carry = %b", a, b, c, sum, carry);
    $dumpfile("full_adder.vcd");
    $dumpvars(0, full_adder_tb);

    a=0;b=0;c=0;
    #1;
    a=0;b=0;c=1;
    #1;
    a=0;b=1;c=0;
    #1;
    a=0;b=1;c=1;
    #1;
    a=1;b=0;c=0;
    #1;
    a=1;b=0;c=1;
    #1;
    a=1;b=1;c=0;
    #1;
    a=1;b=1;c=1;
    #1;

end

endmodule

adder/full_adder.vcd
$date
	Sat Jul 30 00:46:42 2022
$end
$version
	Icarus Verilog
$end
$timescale
	1s
$end
$scope module full_adder_tb $end
$var wire 1 ! sum $end
$var wire 1 " carry $end
$var reg 1 # a $end
$var reg 1 $ b $end
$var reg 1 % c $end
$scope module add1 $end
$var wire 1 # a $end
$var wire 1 $ b $end
$var wire 1 % c $end
$var wire 1 " carry $end
$var wire 1 ! sum $end
$var wire 1 & s1 $end
$var wire 1 ' c2 $end
$var wire 1 ( c1 $end
$scope module ha1 $end
$var wire 1 # a $end
$var wire 1 $ b $end
$var wire 1 ( carry $end
$var wire 1 & sum $end
$upscope $end
$scope module ha2 $end
$var wire 1 & a $end
$var wire 1 % b $end
$var wire 1 ' carry $end
$var wire 1 ! sum $end
$upscope $end
$upscope $end
$upscope $end
$enddefinitions $end
#0
$dumpvars
0(
0'
0&
0%
0$
0#
0"
0!
$end
#1
1!
1%
#2
1&
0%
1$
#3
1"
0!
1'
1%
#4
0"
1!
0'
0%
0$
1#
#5
1"
0!
1'
1%
#6
0'
0&
1(
0%
1$
#7
1!
1%
