exp2/fulladder.v
module fulladder(input A,input B, input Cin ,output S,output Cout);

assign S = (A^B)^Cin;
assign Cout = (A&B)|(Cin&(A^B));

endmodule

dump/exp2/fulladder_tb.v
module fulladder_tb;

wire S,Cout;
reg A,B,Cin;

fulladder c(.A(A),.B(B),.Cin(Cin),.S(S),.Cout(Cout));

initial
begin

$display("Full Adder");

$dumpfile("fulladder.vcd");
$dumpvars(0,fulladder_tb);
$monitor("A = %b | B = %b | Cin = %b | S = %b | Cout = %b",A,B,Cin,S,Cout);

A = 1'b0;
B = 1'b0;
Cin = 1'b0;
#2

Cin = 1'b1;
#2
Cin = 1'b0;
B = 1'b1;
#2
Cin = 1'b1;
#2
Cin = 1'b0;
B = 1'b0;
A = 1'b1;
#2

Cin = 1'b1;
#2
Cin = 1'b0;
B = 1'b1;
#2
Cin = 1'b1;

#2 $finish;
end

endmodule

exp2/fulladder.vcd
$date
	Sat Jul 30 13:47:21 2022
$end
$version
	Icarus Verilog
$end
$timescale
	1s
$end
$scope module fulladder_tb $end
$var wire 1 ! S $end
$var wire 1 " Cout $end
$var reg 1 # A $end
$var reg 1 $ B $end
$var reg 1 % Cin $end
$scope module c $end
$var wire 1 # A $end
$var wire 1 $ B $end
$var wire 1 % Cin $end
$var wire 1 " Cout $end
$var wire 1 ! S $end
$upscope $end
$upscope $end
$enddefinitions $end
#0
$dumpvars
0%
0$
0#
0"
0!
$end
#2
1!
1%
#4
1!
1$
0%
#6
1"
0!
1%
#8
0"
1!
1#
0$
0%
#10
1"
0!
1%
#12
0!
1$
0%
#14
1!
1%
