dump/boolexp/bool3.v
module bool3(input A,input B,input C,input D,output F);

assign F = (~B&D)|(A&(~C))|(C&D);

endmodule

dump/boolexp/bool3_tb.v
module bool3_tb;

wire F;
reg A,B,C,D;

bool3 exp(.A(A),.B(B),.C(C),.D(D),.F(F));

initial
begin
$display("Boolean expression 3");
$dumpfile("bool3.vcd");
$dumpvars(0,bool3_tb);
$monitor("A = %b | B = %b | C = %b | D = %b | F = %b",A,B,C,D,F);

A = 1'b0; B = 1'b0;C = 1'b0;D = 1'b0;
#2

D = 1'b1;
#2
D = 1'b0;C = 1'b1;
#2
D = 1'b1;
#2
D = 1'b0; C = 1'b0; B = 1'b1;
#2

D = 1'b1;
#2
D = 1'b0; C = 1'b1;
#2
D = 1'b1;
#2
A = 1'b1; B = 1'b0;C = 1'b0;D = 1'b0;
#2

D = 1'b1;
#2
D = 1'b0;C = 1'b1;
#2
D = 1'b1;
#2
D = 1'b0; C = 1'b0; B = 1'b1;
#2

D = 1'b1;
#2
D = 1'b0; C = 1'b1;
#2
D = 1'b1;

#2 $finish;
end

endmodule

dump/boolexp/bool3.vcd
$date
	Thu Jul 28 21:18:55 2022
$end
$version
	Icarus Verilog
$end
$timescale
	1s
$end
$scope module bool3_tb $end
$var wire 1 ! F $end
$var reg 1 " A $end
$var reg 1 # B $end
$var reg 1 $ C $end
$var reg 1 % D $end
$scope module exp $end
$var wire 1 " A $end
$var wire 1 # B $end
$var wire 1 $ C $end
$var wire 1 % D $end
$var wire 1 ! F $end
$upscope $end
$upscope $end
$enddefinitions $end
#0
$dumpvars
0%
0$
0#
0"
0!
$end
#2
1!
1%
#4
0!
1$
0%
#6
1!
1%
#8
0!
1#
0$
0%
#10
1%
#12
1$
0%
#14
1!
1%
#16
1!
0%
0$
0#
1"
#18
1%
#20
0!
1$
0%
#22
1!
1%
#24
1!
1#
0$
0%
#26
1%
#28
0!
1$
0%
#30
1!
1%
