boolexp/bool2.v
module bool2(input A,input B,input C,input D,output F);

wire not_A,not_C,BDxnor,out1,out2,out3;

not not1(not_A,A);
xnor xnor1(BDxnor,B,D);
not not2(not_C,C);
or or1(out1,not_C,BDxnor);
and and1(out2,out1,not_A);
and and2(out3,A,C,D);
or or2(F,out3,out2);

endmodule

dump/boolexp/bool2_tb.v
module bool2_tb;

wire F;
reg A,B,C,D;

bool2 exp(.A(A),.B(B),.C(C),.D(D),.F(F));

initial
begin
$display("Boolean expression 2");
$dumpfile("bool2.vcd");
$dumpvars(0,bool2_tb);
$monitor("A = %b | B = %b | C = %b | D = %b | F = %b",A,B,C,D,F);

A = 1'b0; B = 1'b0;C = 1'b0;D = 1'b0;
#2

D = 1'b1;
#2
D = 1'b0;C = 1'b1;
#2
D = 1'b1;
#2
D = 1'b0; C = 1'b0; B = 1'b1;
#2

D = 1'b1;
#2
D = 1'b0; C = 1'b1;
#2
D = 1'b1;
#2
A = 1'b1; B = 1'b0;C = 1'b0;D = 1'b0;
#2

D = 1'b1;
#2
D = 1'b0;C = 1'b1;
#2
D = 1'b1;
#2
D = 1'b0; C = 1'b0; B = 1'b1;
#2

D = 1'b1;
#2
D = 1'b0; C = 1'b1;
#2
D = 1'b1;

#2 $finish;
end

endmodule

dump/boolexp/bool2.vcd
$date
	Thu Jul 28 21:10:17 2022
$end
$version
	Icarus Verilog
$end
$timescale
	1s
$end
$scope module bool2_tb $end
$var wire 1 ! F $end
$var reg 1 " A $end
$var reg 1 # B $end
$var reg 1 $ C $end
$var reg 1 % D $end
$scope module exp $end
$var wire 1 " A $end
$var wire 1 # B $end
$var wire 1 & BDxnor $end
$var wire 1 $ C $end
$var wire 1 % D $end
$var wire 1 ! F $end
$var wire 1 ' not_A $end
$var wire 1 ( not_C $end
$var wire 1 ) out1 $end
$var wire 1 * out2 $end
$var wire 1 + out3 $end
$upscope $end
$upscope $end
$enddefinitions $end
#0
$dumpvars
0+
1*
1)
1(
1'
1&
0%
0$
0#
0"
1!
$end
#2
0&
1%
#4
0(
1&
1$
0%
#6
0!
0*
0)
0&
1%
#8
1!
1*
1)
1(
1#
0$
0%
#10
1&
1%
#12
0!
0*
0)
0(
0&
1$
0%
#14
1!
1*
1)
1&
1%
#16
0!
0*
1(
0'
0%
0$
0#
1"
#18
0&
1%
#20
0(
1&
1$
0%
#22
0)
1!
0&
1+
1%
#24
1)
0!
1(
0+
1#
0$
0%
#26
1&
1%
#28
0)
0(
0&
1$
0%
#30
1)
1!
1&
1+
1%
