dump/adder-2/exp2/ha1.v
module ha1(x,y,s,c);

input x,y;
output s,c;

xor sum(s,x,y);
and carry(c,x,y);

endmodule

adder-2/exp2/fa1.v
`include "ha1.v"

module fa1(a,b,cin,s,cout);

input a,b,cin;
output cout,s;

wire sum1,carry1,carry2;

ha1 halfA1(a,b,sum1,carry1);
ha1 halfA2(sum1,cin,s,carry2);
or or1(cout,carry1,carry2);

endmodule

adder-2/exp2/fa1_tb.v
module fa1_tb;

reg a,b,cin;
wire s,cout;

fa1 fA1(.a(a),.b(b),.cin(cin),.s(s),.cout(cout));

initial begin
    $display("Full Adder");
    $dumpfile("fa1.vcd");
    $dumpvars(0,fa1_tb);
    $monitor("A = %b | B = %b | Cin = %b | S = %b | Cout = %b",a,b,cin,s,cout);

    a = 1'b0;
    b = 1'b0;
    cin = 1'b0;
    #2

    cin = 1'b1;
    #2

    b = 1'b1;
    cin = 1'b0;
    #2

    cin = 1'b1;
    #2

    a = 1'b1;
    b = 1'b0;
    cin = 1'b0;
    #2

    cin = 1'b1;
    #2

    b = 1'b1;
    cin = 1'b0;
    #2

    cin = 1'b1;
    #2
    $finish;

end

endmodule

adder-2/exp2/fa1.vcd
$date
	Tue Aug 02 10:17:09 2022
$end
$version
	Icarus Verilog
$end
$timescale
	1s
$end
$scope module fa1_tb $end
$var wire 1 ! s $end
$var wire 1 " cout $end
$var reg 1 # a $end
$var reg 1 $ b $end
$var reg 1 % cin $end
$scope module fA1 $end
$var wire 1 # a $end
$var wire 1 $ b $end
$var wire 1 % cin $end
$var wire 1 " cout $end
$var wire 1 & sum1 $end
$var wire 1 ! s $end
$var wire 1 ' carry2 $end
$var wire 1 ( carry1 $end
$scope module halfA1 $end
$var wire 1 ( c $end
$var wire 1 & s $end
$var wire 1 # x $end
$var wire 1 $ y $end
$upscope $end
$scope module halfA2 $end
$var wire 1 ' c $end
$var wire 1 ! s $end
$var wire 1 & x $end
$var wire 1 % y $end
$upscope $end
$upscope $end
$upscope $end
$enddefinitions $end
$comment Show the parameter values. $end
$dumpall
$end
#0
$dumpvars
0(
0'
0&
0%
0$
0#
0"
0!
$end
#2
1!
1%
#4
1&
0%
1$
#6
1"
0!
1'
1%
#8
0"
1!
0'
0%
0$
1#
#10
1"
0!
1'
1%
#12
0'
0&
1(
0%
1$
#14
1!
1%
