converter/binary_to_gray.v
module binary_to_gray(b0,b1,b2,b3,g0,g1,g2,g3);
input b0,b1,b2,b3;
output g0,g1,g2,g3;

xor x1(g0,b0,b1);
xor x2(g1,b1,b2);
xor x3(g2,b2,b3);
and a(g3,b3,b3);


endmodule

converter/binary_to_gray_tb.v
module binary_to_gray_tb;

reg b0,b1,b2,b3;
wire g0,g1,g2,g3;

binary_to_gray conv1(b0,b1,b2,b3,g0,g1,g2,g3);
initial
begin
    $monitor("b3 = %b, b2 = %b, b1 = %b, b0 = %b, g3 = %b, g2 = %b, g1 = %b, g0 = %b", b3, b2, b1, b0, g3, g2, g1, g0);
    $dumpfile("binary_to_gray_tb.vcd");
    $dumpvars(0,binary_to_gray_tb);
    b3=0;b2=0;b1=0;b0=0;
    #1;
    b3=0;b2=0;b1=0;b0=1;
    #1;
    b3=0;b2=0;b1=1;b0=0;
    #1;
    b3=0;b2=0;b1=1;b0=1;
    #1;
    b3=0;b2=1;b1=0;b0=0;
    #1;
    b3=0;b2=1;b1=0;b0=1;
    #1;
    b3=0;b2=1;b1=1;b0=0;
    #1;
    b3=0;b2=1;b1=1;b0=1;
    #1;
    b3=1;b2=0;b1=0;b0=0;
    #1;
    b3=1;b2=0;b1=0;b0=1;
    #1;
    b3=1;b2=0;b1=1;b0=0;
    #1;
    b3=1;b2=0;b1=1;b0=1;
    #1;
    b3=1;b2=1;b1=0;b0=0;
    #1;
    b3=1;b2=1;b1=0;b0=1;
    #1;
    b3=1;b2=1;b1=1;b0=0;
    #1;
    b3=1;b2=1;b1=1;b0=1;
    #1;

end


endmodule

converter/binary_to_gray_tb.vcd
$date
	Fri Jul 29 23:56:24 2022
$end
$version
	Icarus Verilog
$end
$timescale
	1s
$end
$scope module binary_to_gray_tb $end
$var wire 1 ! g3 $end
$var wire 1 " g2 $end
$var wire 1 # g1 $end
$var wire 1 $ g0 $end
$var reg 1 % b0 $end
$var reg 1 & b1 $end
$var reg 1 ' b2 $end
$var reg 1 ( b3 $end
$scope module conv1 $end
$var wire 1 % b0 $end
$var wire 1 & b1 $end
$var wire 1 ' b2 $end
$var wire 1 ( b3 $end
$var wire 1 $ g0 $end
$var wire 1 # g1 $end
$var wire 1 " g2 $end
$var wire 1 ! g3 $end
$upscope $end
$upscope $end
$enddefinitions $end
#0
$dumpvars
0(
0'
0&
0%
0$
0#
0"
0!
$end
#1
1$
1%
#2
1#
0%
1&
#3
0$
1%
#4
1"
0%
0&
1'
#5
1$
1%
#6
0#
0%
1&
#7
0$
1%
#8
1!
0%
0&
0'
1(
#9
1$
1%
#10
1#
0%
1&
#11
0$
1%
#12
0"
0%
0&
1'
#13
1$
1%
#14
0#
0%
1&
#15
0$
1%
