converter/gray_to_binary.v
module gray_to_binary(b0,b1,b2,b3,g0,g1,g2,g3);
output b0,b1,b2,b3;
input g0,g1,g2,g3;

assign b3 = g3;
xor(b2, g3, g2);
xor(b1, g3, g2, g1);
xor(b0, g3, g2, g1, g0);

endmodule

converter/gray_to_binary_tb.v
module gray_to_binary_tb;

wire b0,b1,b2,b3;
reg g0,g1,g2,g3;

gray_to_binary conv1(b0,b1,b2,b3,g0,g1,g2,g3);
initial
begin
    $monitor("g3 = %b, g2 = %b, g1 = %b, g0 = %b, b3 = %b, b2 = %b, b1 = %b, b0 = %b", g3, g2, g1, g0, b3, b2, b1, b0);
    $dumpfile("gray_to_binary_tb.vcd");
    $dumpvars(0,gray_to_binary_tb);
    g3=0;g2=0;g1=0;g0=0;
    #1;
    g3=0;g2=0;g1=0;g0=1;
    #1;
    g3=0;g2=0;g1=1;g0=0;
    #1;
    g3=0;g2=0;g1=1;g0=1;
    #1;
    g3=0;g2=1;g1=0;g0=0;
    #1;
    g3=0;g2=1;g1=0;g0=1;
    #1;
    g3=0;g2=1;g1=1;g0=0;
    #1;
    g3=0;g2=1;g1=1;g0=1;
    #1;
    g3=1;g2=0;g1=0;g0=0;
    #1;
    g3=1;g2=0;g1=0;g0=1;
    #1;
    g3=1;g2=0;g1=1;g0=0;
    #1;
    g3=1;g2=0;g1=1;g0=1;
    #1;
    g3=1;g2=1;g1=0;g0=0;
    #1;
    g3=1;g2=1;g1=0;g0=1;
    #1;
    g3=1;g2=1;g1=1;g0=0;
    #1;
    g3=1;g2=1;g1=1;g0=1;
    #1;

end


endmodule

converter/gray_to_binary_tb.vcd
$date
	Sat Jul 30 00:04:16 2022
$end
$version
	Icarus Verilog
$end
$timescale
	1s
$end
$scope module gray_to_binary_tb $end
$var wire 1 ! b3 $end
$var wire 1 " b2 $end
$var wire 1 # b1 $end
$var wire 1 $ b0 $end
$var reg 1 % g0 $end
$var reg 1 & g1 $end
$var reg 1 ' g2 $end
$var reg 1 ( g3 $end
$scope module conv1 $end
$var wire 1 $ b0 $end
$var wire 1 # b1 $end
$var wire 1 " b2 $end
$var wire 1 ! b3 $end
$var wire 1 % g0 $end
$var wire 1 & g1 $end
$var wire 1 ' g2 $end
$var wire 1 ( g3 $end
$upscope $end
$upscope $end
$enddefinitions $end
#0
$dumpvars
0(
0'
0&
0%
0$
0#
0"
0!
$end
#1
1$
1%
#2
1#
0%
1&
#3
0$
1%
#4
1"
1$
0%
0&
1'
#5
0$
1%
#6
0#
0%
1&
#7
1$
1%
#8
1#
0%
0&
0'
1!
1(
#9
0$
1%
#10
0#
0%
1&
#11
1$
1%
#12
0"
0$
0%
0&
1'
#13
1$
1%
#14
1#
0%
1&
#15
0$
1%
