boolexp/bool1.v
module bool1(input A,input B,input C, output F);

assign F = ((~A)&B)|(~C);

endmodule

boolexp/bool1_tb.v
module bool1_tb;

wire F;
reg A,B,C;

bool1 exp(.A(A),.B(B),.C(C),.F(F));

initial
begin
$display("Boolean expression 1");
$dumpfile("bool1.vcd");
$dumpvars(0,bool1_tb);
$monitor("A = %b | B = %b | C = %b | F = %b",A,B,C,F);

A = 1'b0;
B = 1'b0;
C = 1'b0;
#2

C = 1'b1;
#2
C = 1'b0;
B = 1'b1;
#2
C = 1'b1;
#2
C = 1'b0;
B = 1'b0;
A = 1'b1;
#2

C = 1'b1;
#2
C = 1'b0;
B = 1'b1;
#2
C = 1'b1;

#2 $finish;
end

endmodule

boolexp/bool1.vcd
$date
	Sat Jul 30 13:37:52 2022
$end
$version
	Icarus Verilog
$end
$timescale
	1s
$end
$scope module bool1_tb $end
$var wire 1 ! F $end
$var reg 1 " A $end
$var reg 1 # B $end
$var reg 1 $ C $end
$scope module exp $end
$var wire 1 " A $end
$var wire 1 # B $end
$var wire 1 $ C $end
$var wire 1 ! F $end
$upscope $end
$upscope $end
$enddefinitions $end
#0
$dumpvars
0$
0#
0"
1!
$end
#2
0!
1$
#4
1!
1#
0$
#6
1$
#8
1"
0#
0$
#10
0!
1$
#12
1!
1#
0$
#14
0!
1$
