exp3/bintogray.v
module bintogray(input B3,input B2,input B1,input B0,output G3,output G2,output G1,output G0);

assign G3 = B3;
assign G2 = B3^B2;
assign G1 = B1^B2;
assign G0 = B1^B0;

endmodule

dump/exp3/bintogray_tb.v
module bintogray_tb;

wire G0,G1,G2,G3;
reg B0,B1,B2,B3;

bintogray c(.B3(B3),.B2(B2),.B1(B1),.B0(B0),.G3(G3),.G2(G2),.G1(G1),.G0(G0));

initial
begin

$display("Binary to Gray");

$dumpfile("bintogray.vcd");
$dumpvars(0,bintogray_tb);
$monitor("B3 = %b | B2 = %b | B1 = %b | B0 = %b | G3 = %b | G2 = %b | G1 = %b | G0 = %b",B3,B2,B1,B0,G3,G2,G1,G0);

B3 = 1'b0; B2 = 1'b0;B1 = 1'b0;B0 = 1'b0;
#2

B0 = 1'b1;
#2
B0 = 1'b0;B1 = 1'b1;
#2
B0 = 1'b1;
#2
B0 = 1'b0; B1 = 1'b0; B2 = 1'b1;
#2

B0 = 1'b1;
#2
B0 = 1'b0; B1 = 1'b1;
#2
B0 = 1'b1;
#2
B3 = 1'b1; B2 = 1'b0;B1 = 1'b0;B0 = 1'b0;
#2

B0 = 1'b1;
#2
B0 = 1'b0;B1 = 1'b1;
#2
B0 = 1'b1;
#2
B0 = 1'b0; B1 = 1'b0; B2 = 1'b1;
#2

B0 = 1'b1;
#2
B0 = 1'b0; B1 = 1'b1;
#2
B0 = 1'b1;

#2 $finish;
end

endmodule

exp3/bintogray.vcd
$date
	Sat Jul 30 13:48:09 2022
$end
$version
	Icarus Verilog
$end
$timescale
	1s
$end
$scope module bintogray_tb $end
$var wire 1 ! G3 $end
$var wire 1 " G2 $end
$var wire 1 # G1 $end
$var wire 1 $ G0 $end
$var reg 1 % B0 $end
$var reg 1 & B1 $end
$var reg 1 ' B2 $end
$var reg 1 ( B3 $end
$scope module c $end
$var wire 1 % B0 $end
$var wire 1 & B1 $end
$var wire 1 ' B2 $end
$var wire 1 ( B3 $end
$var wire 1 $ G0 $end
$var wire 1 # G1 $end
$var wire 1 " G2 $end
$var wire 1 ! G3 $end
$upscope $end
$upscope $end
$enddefinitions $end
#0
$dumpvars
0(
0'
0&
0%
0$
0#
0"
0!
$end
#2
1$
1%
#4
1#
1&
0%
#6
0$
1%
#8
1"
1'
0&
0%
#10
1$
1%
#12
0#
1&
0%
#14
0$
1%
#16
0%
0&
0'
1!
1(
#18
1$
1%
#20
1#
1&
0%
#22
0$
1%
#24
0"
1'
0&
0%
#26
1$
1%
#28
0#
1&
0%
#30
0$
1%
