exp3/graytobin.v
module graytobin(input G3,input G2,input G1,input G0,output B3,output B2,output B1,output B0);

assign B3 = G3;
assign B2 = G3^G2;
assign B1 = G3^G2^G1;
assign B0 = G3^G2^G1^G0;

endmodule

dump/exp3/graytobin_tb.v
module graytobin_tb;

reg G0,G1,G2,G3;
wire B0,B1,B2,B3;

graytobin c(.G3(G3),.G2(G2),.G1(G1),.G0(G0),.B3(B3),.B2(B2),.B1(B1),.B0(B0));

initial
begin

$display("Gray to Binary");

$dumpfile("graytobin.vcd");
$dumpvars(0,graytobin_tb);
$monitor("G3 = %b | G2 = %b | G1 = %b | G0 = %b | B3 = %b | B2 = %b | B1 = %b | B0 = %b",G3,G2,G1,G0,B3,B2,B1,B0);

G3 = 1'b0; G2 = 1'b0;G1 = 1'b0;G0 = 1'b0;
#2

G0 = 1'b1;
#2
G0 = 1'b0;G1 = 1'b1;
#2
G0 = 1'b1;
#2
G0 = 1'b0; G1 = 1'b0; G2 = 1'b1;
#2

G0 = 1'b1;
#2
G0 = 1'b0; G1 = 1'b1;
#2
G0 = 1'b1;
#2
G3 = 1'b1; G2 = 1'b0;G1 = 1'b0;G0 = 1'b0;
#2

G0 = 1'b1;
#2
G0 = 1'b0;G1 = 1'b1;
#2
G0 = 1'b1;
#2
G0 = 1'b0; G1 = 1'b0; G2 = 1'b1;
#2

G0 = 1'b1;
#2
G0 = 1'b0; G1 = 1'b1;
#2
G0 = 1'b1;
#2 $finish;
end

endmodule

dump/exp3/graytobin.vcd
$date
	Sat Jul 30 13:48:12 2022
$end
$version
	Icarus Verilog
$end
$timescale
	1s
$end
$scope module graytobin_tb $end
$var wire 1 ! B3 $end
$var wire 1 " B2 $end
$var wire 1 # B1 $end
$var wire 1 $ B0 $end
$var reg 1 % G0 $end
$var reg 1 & G1 $end
$var reg 1 ' G2 $end
$var reg 1 ( G3 $end
$scope module c $end
$var wire 1 $ B0 $end
$var wire 1 # B1 $end
$var wire 1 " B2 $end
$var wire 1 ! B3 $end
$var wire 1 % G0 $end
$var wire 1 & G1 $end
$var wire 1 ' G2 $end
$var wire 1 ( G3 $end
$upscope $end
$upscope $end
$enddefinitions $end
#0
$dumpvars
0(
0'
0&
0%
0$
0#
0"
0!
$end
#2
1$
1%
#4
1#
1$
1&
0%
#6
0$
1%
#8
1"
1#
1$
1'
0&
0%
#10
0$
1%
#12
0#
0$
1&
0%
#14
1$
1%
#16
1#
0%
0&
0'
1!
1(
#18
0$
1%
#20
0#
0$
1&
0%
#22
1$
1%
#24
0"
0#
0$
1'
0&
0%
#26
1$
1%
#28
1#
1$
1&
0%
#30
0$
1%
